<?xml version="1.0" encoding="UTF-8" ?>

<Data>
<Game>
<id>38234</id>
<GameTitle>Sky Skipper</GameTitle>
<ReleaseDate>11/01/1983</ReleaseDate>
<Platform>Atari 2600</Platform>
</Game>
<Game>
<id>40772</id>
<GameTitle>Sky Skipper</GameTitle>
<ReleaseDate>01/01/1981</ReleaseDate>
<Platform>Arcade</Platform>
</Game>
<Game>
<id>45570</id>
<GameTitle>Sky Base</GameTitle>
<ReleaseDate>05/01/1982</ReleaseDate>
<Platform>Arcade</Platform>
</Game>
<Game>
<id>28153</id>
<GameTitle>Sky Dancers</GameTitle>
<ReleaseDate>10/25/2005</ReleaseDate>
<Platform>Nintendo Game Boy Advance</Platform>
</Game>
<Game>
<id>28975</id>
<GameTitle>Sky Rogue</GameTitle>
<ReleaseDate></ReleaseDate>
<Platform>PC</Platform>
</Game>
<Game>
<id>50137</id>
<GameTitle>Sky Raider</GameTitle>
<ReleaseDate>01/01/1978</ReleaseDate>
<Platform>Arcade</Platform>
</Game>
<Game>
<id>45568</id>
<GameTitle>Sky Alert</GameTitle>
<ReleaseDate>05/01/1992</ReleaseDate>
<Platform>Arcade</Platform>
</Game>
<Game>
<id>45573</id>
<GameTitle>Sky Soldiers</GameTitle>
<ReleaseDate>05/03/1988</ReleaseDate>
<Platform>Arcade</Platform>
</Game>
<Game>
<id>24844</id>
<GameTitle>Sky Ace</GameTitle>
<ReleaseDate>01/27/1993</ReleaseDate>
<Platform>Nintendo Game Boy</Platform>
</Game>
<Game>
<id>38821</id>
<GameTitle>Sky Diver</GameTitle>
<ReleaseDate>10/01/1978</ReleaseDate>
<Platform>Arcade</Platform>
</Game>
<Game>
<id>44346</id>
<GameTitle>Sky Kid</GameTitle>
<ReleaseDate>12/01/1985</ReleaseDate>
<Platform>Nintendo Entertainment System (NES)</Platform>
</Game>
<Game>
<id>35631</id>
<GameTitle>Sky Jaguar</GameTitle>
<ReleaseDate>01/01/1984</ReleaseDate>
<Platform>MSX</Platform>
</Game>
<Game>
<id>9811</id>
<GameTitle>Sky Odyssey</GameTitle>
<ReleaseDate>11/15/2000</ReleaseDate>
<Platform>Sony Playstation 2</Platform>
</Game>
<Game>
<id>11345</id>
<GameTitle>Sky Target</GameTitle>
<ReleaseDate>06/01/1997</ReleaseDate>
<Platform>Sega Saturn</Platform>
</Game>
<Game>
<id>27277</id>
<GameTitle>Sky Destroyer</GameTitle>
<ReleaseDate>11/14/1985</ReleaseDate>
<Platform>Nintendo Entertainment System (NES)</Platform>
</Game>
<Game>
<id>14983</id>
<GameTitle>Sky Target</GameTitle>
<ReleaseDate>01/01/1995</ReleaseDate>
<Platform>Arcade</Platform>
</Game>
<Game>
<id>45572</id>
<GameTitle>Sky Lancer</GameTitle>
<ReleaseDate>05/03/1983</ReleaseDate>
<Platform>Arcade</Platform>
</Game>
<Game>
<id>38820</id>
<GameTitle>Sky Fox</GameTitle>
<ReleaseDate>10/01/1987</ReleaseDate>
<Platform>Arcade</Platform>
</Game>
<Game>
<id>40954</id>
<GameTitle>Sky Kid</GameTitle>
<ReleaseDate></ReleaseDate>
<Platform>Epoch Super Cassette Vision</Platform>
</Game>
<Game>
<id>45567</id>
<GameTitle>Sky Adventure</GameTitle>
<ReleaseDate>05/03/1989</ReleaseDate>
<Platform>Arcade</Platform>
</Game>
<Game>
<id>48408</id>
<GameTitle>Sky Galdo</GameTitle>
<ReleaseDate>08/12/1986</ReleaseDate>
<Platform>MSX</Platform>
</Game>
<Game>
<id>33223</id>
<GameTitle>Sky Smasher</GameTitle>
<ReleaseDate>01/01/1990</ReleaseDate>
<Platform>Arcade</Platform>
</Game>
<Game>
<id>34928</id>
<GameTitle>Sky Patrol</GameTitle>
<ReleaseDate></ReleaseDate>
<Platform>Atari 2600</Platform>
</Game>
<Game>
<id>2080</id>
<GameTitle>Sky Shark</GameTitle>
<ReleaseDate>01/01/1989</ReleaseDate>
<Platform>Nintendo Entertainment System (NES)</Platform>
</Game>
<Game>
<id>15891</id>
<GameTitle>Sky Jinks</GameTitle>
<ReleaseDate>01/01/1982</ReleaseDate>
<Platform>Atari 2600</Platform>
</Game>
<Game>
<id>16611</id>
<GameTitle>Sky Fighter</GameTitle>
<ReleaseDate>11/16/2010</ReleaseDate>
<Platform>Sony Playstation 3</Platform>
</Game>
<Game>
<id>18542</id>
<GameTitle>Sky Nations</GameTitle>
<ReleaseDate>08/11/2013</ReleaseDate>
<Platform>PC</Platform>
</Game>
<Game>
<id>45571</id>
<GameTitle>Sky Bumper</GameTitle>
<ReleaseDate>05/05/1982</ReleaseDate>
<Platform>Arcade</Platform>
</Game>
<Game>
<id>45569</id>
<GameTitle>Sky Army</GameTitle>
<ReleaseDate>05/06/1982</ReleaseDate>
<Platform>Arcade</Platform>
</Game>
<Game>
<id>33025</id>
<GameTitle>Rodea: The Sky Soldier</GameTitle>
<ReleaseDate>11/10/2015</ReleaseDate>
<Platform>Nintendo Wii U</Platform>
</Game>
<Game>
<id>15693</id>
<GameTitle>Iron Sky Invasion</GameTitle>
<ReleaseDate>12/12/2012</ReleaseDate>
<Platform>Microsoft Xbox 360</Platform>
</Game>
<Game>
<id>49128</id>
<GameTitle>The Sky is Falling</GameTitle>
<ReleaseDate>01/01/1981</ReleaseDate>
<Platform>Commodore VIC-20</Platform>
</Game>
<Game>
<id>40047</id>
<GameTitle>Rodea: The Sky Soldier</GameTitle>
<ReleaseDate>11/10/2015</ReleaseDate>
<Platform>Nintendo 3DS</Platform>
</Game>
<Game>
<id>43510</id>
<GameTitle>Kid Adventures: Sky Captain</GameTitle>
<ReleaseDate></ReleaseDate>
<Platform>Nintendo Wii</Platform>
</Game>
<Game>
<id>15691</id>
<GameTitle>Iron Sky Invasion</GameTitle>
<ReleaseDate>12/12/2012</ReleaseDate>
<Platform>Sony Playstation 3</Platform>
</Game>
<Game>
<id>29274</id>
<GameTitle>No Man's Sky</GameTitle>
<ReleaseDate>08/09/2016</ReleaseDate>
<Platform>Sony Playstation 4</Platform>
</Game>
<Game>
<id>31596</id>
<GameTitle>Sky Gamblers: Storm Raiders</GameTitle>
<ReleaseDate></ReleaseDate>
<Platform>Android</Platform>
</Game>
<Game>
<id>42321</id>
<GameTitle>Beneath a Steel Sky</GameTitle>
<ReleaseDate>03/01/1994</ReleaseDate>
<Platform>PC</Platform>
</Game>
<Game>
<id>45724</id>
<GameTitle>Vs. Super Sky Kid</GameTitle>
<ReleaseDate>05/01/1986</ReleaseDate>
<Platform>Arcade</Platform>
</Game>
<Game>
<id>1519</id>
<GameTitle>Big Sky Trooper</GameTitle>
<ReleaseDate>10/01/1995</ReleaseDate>
<Platform>Super Nintendo (SNES)</Platform>
</Game>
<Game>
<id>30287</id>
<GameTitle>Sky Gamblers: Storm Raiders</GameTitle>
<ReleaseDate></ReleaseDate>
<Platform>iOS</Platform>
</Game>
<Game>
<id>34715</id>
<GameTitle>Hanii in the Sky</GameTitle>
<ReleaseDate>03/01/1989</ReleaseDate>
<Platform>TurboGrafx 16</Platform>
</Game>
<Game>
<id>33024</id>
<GameTitle>Rodea The Sky Soldier</GameTitle>
<ReleaseDate>11/10/2015</ReleaseDate>
<Platform>Nintendo Wii</Platform>
</Game>
<Game>
<id>101</id>
<GameTitle>S.T.A.L.K.E.R.: Clear Sky</GameTitle>
<ReleaseDate>09/05/2008</ReleaseDate>
<Platform>PC</Platform>
</Game>
<Game>
<id>15692</id>
<GameTitle>Iron Sky Invasion</GameTitle>
<ReleaseDate>12/12/2012</ReleaseDate>
<Platform>PC</Platform>
</Game>
<Game>
<id>19788</id>
<GameTitle>Sky Maze 3D</GameTitle>
<ReleaseDate>03/28/2013</ReleaseDate>
<Platform>Ouya</Platform>
</Game>
<Game>
<id>23246</id>
<GameTitle>Summoners War: Sky Arena</GameTitle>
<ReleaseDate></ReleaseDate>
<Platform>Android</Platform>
</Game>
<Game>
<id>49564</id>
<GameTitle>Knights of the Sky</GameTitle>
<ReleaseDate>09/10/1991</ReleaseDate>
<Platform>Amiga</Platform>
</Game>
<Game>
<id>45574</id>
<GameTitle>Sky Kid Deluxe</GameTitle>
<ReleaseDate>02/01/1986</ReleaseDate>
<Platform>Arcade</Platform>
</Game>
<Game>
<id>34339</id>
<GameTitle>Sky Diver (Dare Diver)</GameTitle>
<ReleaseDate>01/01/1978</ReleaseDate>
<Platform>Atari 2600</Platform>
</Game>
<Game>
<id>40610</id>
<GameTitle>Hani In The Sky</GameTitle>
<ReleaseDate>03/01/1989</ReleaseDate>
<Platform>TurboGrafx 16</Platform>
</Game>
<Game>
<id>9947</id>
<GameTitle>Really Big Sky</GameTitle>
<ReleaseDate>07/01/2011</ReleaseDate>
<Platform>PC</Platform>
</Game>
<Game>
<id>10170</id>
<GameTitle>Beneath a Steel Sky</GameTitle>
<ReleaseDate></ReleaseDate>
<Platform>Amiga</Platform>
</Game>
<Game>
<id>15694</id>
<GameTitle>Iron Sky Invasion</GameTitle>
<ReleaseDate>12/12/2012</ReleaseDate>
<Platform>Mac OS</Platform>
</Game>
<Game>
<id>18751</id>
<GameTitle>No Man's Sky</GameTitle>
<ReleaseDate>08/09/2016</ReleaseDate>
<Platform>PC</Platform>
</Game>
<Game>
<id>49523</id>
<GameTitle>Knights of the sky</GameTitle>
<ReleaseDate>09/04/1990</ReleaseDate>
<Platform>PC</Platform>
</Game>
<Game>
<id>42386</id>
<GameTitle>WWI: Aces of the Sky</GameTitle>
<ReleaseDate>09/01/2006</ReleaseDate>
<Platform>Sony Playstation 2</Platform>
</Game>
<Game>
<id>43536</id>
<GameTitle>Vroom In The Night Sky</GameTitle>
<ReleaseDate>03/03/2017</ReleaseDate>
<Platform>Nintendo Switch</Platform>
</Game>
<Game>
<id>10071</id>
<GameTitle>Beneath a Steel Sky (1994)</GameTitle>
<ReleaseDate>03/01/1994</ReleaseDate>
<Platform>PC</Platform>
</Game>
<Game>
<id>16788</id>
<GameTitle>The Sky Crawlers: Innocent Aces</GameTitle>
<ReleaseDate>01/12/2010</ReleaseDate>
<Platform>Nintendo Wii</Platform>
</Game>
<Game>
<id>33649</id>
<GameTitle>Aworg: Hero in the Sky</GameTitle>
<ReleaseDate>01/01/1991</ReleaseDate>
<Platform>Sega Genesis</Platform>
</Game>
<Game>
<id>25398</id>
<GameTitle>Zeppelin: Giants of the Sky</GameTitle>
<ReleaseDate>01/01/1995</ReleaseDate>
<Platform>PC</Platform>
</Game>
<Game>
<id>50477</id>
<GameTitle>No Man's Sky Limited Edition</GameTitle>
<ReleaseDate>08/09/2016</ReleaseDate>
<Platform>Sony Playstation 4</Platform>
</Game>
<Game>
<id>19895</id>
<GameTitle>Atelier Escha &amp; Logy: Alchemist of Dusk Sky</GameTitle>
<ReleaseDate>03/07/2014</ReleaseDate>
<Platform>Sony Playstation 3</Platform>
</Game>
<Game>
<id>21454</id>
<GameTitle>Pokémon Mystery Dungeon: Explorers of Sky</GameTitle>
<ReleaseDate>10/12/2009</ReleaseDate>
<Platform>Nintendo DS</Platform>
</Game>
<Game>
<id>31167</id>
<GameTitle>B-17 Fortress in the Sky</GameTitle>
<ReleaseDate>06/19/2007</ReleaseDate>
<Platform>Nintendo DS</Platform>
</Game>
<Game>
<id>34674</id>
<GameTitle>Atelier Escha &amp; Logy Plus: Alchemist of Dusk Sky</GameTitle>
<ReleaseDate>01/19/2016</ReleaseDate>
<Platform>Sony Playstation Vita</Platform>
</Game>
<Game>
<id>34355</id>
<GameTitle>The Legend of Heroes: Trails in the Sky SC</GameTitle>
<ReleaseDate>10/29/2015</ReleaseDate>
<Platform>Sony Playstation Portable</Platform>
</Game>
<Game>
<id>41848</id>
<GameTitle>Exist Archive: The Other Side of the Sky</GameTitle>
<ReleaseDate>10/18/2016</ReleaseDate>
<Platform>Sony Playstation 4</Platform>
</Game>
<Game>
<id>40337</id>
<GameTitle>Exist Archive: The Other Side of The Sky</GameTitle>
<ReleaseDate>10/18/2016</ReleaseDate>
<Platform>Sony Playstation Vita</Platform>
</Game>
<Game>
<id>32308</id>
<GameTitle>The Legend of Heroes: Trails in the Sky SC</GameTitle>
<ReleaseDate>10/29/2015</ReleaseDate>
<Platform>PC</Platform>
</Game>
<Game>
<id>22750</id>
<GameTitle>The Legend of Heroes: Trails in the Sky</GameTitle>
<ReleaseDate>07/29/2015</ReleaseDate>
<Platform>PC</Platform>
</Game>
<Game>
<id>13218</id>
<GameTitle>The Legend of Heroes: Trails in the Sky</GameTitle>
<ReleaseDate>03/29/2011</ReleaseDate>
<Platform>Sony Playstation Portable</Platform>
</Game>
</Data>
